stormvogel/__init__.py
stormvogel/autoscale_svg.py
stormvogel/bird.py
stormvogel/communication_server.py
stormvogel/dict_editor.py
stormvogel/displayable.py
stormvogel/examples/__init__.py
stormvogel/examples/car.py
stormvogel/examples/debugging.py
stormvogel/examples/die.py
stormvogel/examples/end_components.py
stormvogel/examples/knuth_yao_imc.py
stormvogel/examples/knuth_yao_pmc.py
stormvogel/examples/lion.py
stormvogel/examples/monty_hall.py
stormvogel/examples/monty_hall_pomdp.py
stormvogel/examples/monty_hall_should.py
stormvogel/examples/nuclear_fusion_ctmc.py
stormvogel/examples/stormpy_examples/__init__.py
stormvogel/examples/stormpy_examples/stormpy_ctmc.py
stormvogel/examples/stormpy_examples/stormpy_dtmc.py
stormvogel/examples/stormpy_examples/stormpy_ma.py
stormvogel/examples/stormpy_examples/stormpy_mdp.py
stormvogel/examples/stormpy_examples/stormpy_pmc.py
stormvogel/examples/stormpy_examples/stormpy_pomdp.py
stormvogel/examples/study.py
stormvogel/extensions/__init__.py
stormvogel/extensions/ec_elimination.py
stormvogel/extensions/gifs.py
stormvogel/extensions/gym_grid.py
stormvogel/extensions/gym_sampling.py
stormvogel/extensions/visual_algos.py
stormvogel/graph.py
stormvogel/html_generation.py
stormvogel/layout.py
stormvogel/layout_editor.py
stormvogel/layouts/default.json
stormvogel/layouts/schema.json
stormvogel/layouts/sv.json
stormvogel/model.py
stormvogel/parametric.py
stormvogel/property_builder.py
stormvogel/rdict.py
stormvogel/result.py
stormvogel/show.py
stormvogel/simulator.py
stormvogel/stormpy_utils/__init__.py
stormvogel/stormpy_utils/convert_results.py
stormvogel/stormpy_utils/magic.py
stormvogel/stormpy_utils/mapping.py
stormvogel/stormpy_utils/model_checking.py
stormvogel/svgcanvas.js
stormvogel/vis-network-9.1.9-patched.js
stormvogel/visualization.py
stormvogel-0.10.0.dist-info/METADATA
stormvogel-0.10.0.dist-info/WHEEL
stormvogel-0.10.0.dist-info/licenses/LICENSE
stormvogel-0.10.0.dist-info/RECORD
