Metadata-Version: 2.4
Name: stormvogel
Version: 0.10.0
Summary: Probabilistic Model Checking for almost everyone
License: GPLv3
License-File: LICENSE
Author: The stormvogel team
Requires-Python: >=3.12,<4.0
Classifier: License :: Other/Proprietary License
Classifier: Programming Language :: Python :: 3
Classifier: Programming Language :: Python :: 3.12
Classifier: Programming Language :: Python :: 3.13
Classifier: Programming Language :: Python :: 3.14
Requires-Dist: anyio (>=4.6.0,<5.0.0)
Requires-Dist: bidict (>=0.23.1,<0.24.0)
Requires-Dist: deprecated (>=1.2.18,<2.0.0)
Requires-Dist: gymnasium (>=1.1.1,<2.0.0)
Requires-Dist: imageio (>=2.37.0,<3.0.0)
Requires-Dist: ipywidgets (>=8.1.3,<9.0.0)
Requires-Dist: jupyter (>=1.1.1,<2.0.0)
Requires-Dist: lxml (>=5.3.2,<6.0.0)
Requires-Dist: matplotlib (>=3.9.2,<4.0.0)
Requires-Dist: mock (>=5.1.0,<6.0.0)
Requires-Dist: nbdime (>=4.0.2,<5.0.0)
Requires-Dist: nbmake (>=1.5.4,<2.0.0)
Requires-Dist: nbval (>=0.11.0,<0.12.0)
Requires-Dist: networkx (>=3.4.2,<4.0.0)
Requires-Dist: numpy (>=2.0.1,<3.0.0)
Requires-Dist: pandas (>=2.2.2,<3.0.0)
Requires-Dist: pygame (>=2.6.1,<3.0.0)
Requires-Dist: pytest-mock (>=3.14.0,<4.0.0)
Requires-Dist: pyvis (>=0.3.2,<0.4.0)
Requires-Dist: sphinx-autoapi (>=3.3.1,<4.0.0)
Requires-Dist: svgpathtools (>=1.6.1,<2.0.0)
